{
  "id": "frame_1889",
  "user": "NPC-AI",
  "frame": "frame_1889",
  "detected_objects": [
    {
      "cls": 0,
      "landing_status": -1,
      "top_left_x": 1424.701416015625,
      "top_left_y": 241.62933349609375,
      "bottom_right_x": 1660.069091796875,
      "bottom_right_y": 339.78521728515625
    },
    {
      "cls": 0,
      "landing_status": -1,
      "top_left_x": 684.97021484375,
      "top_left_y": 344.7562255859375,
      "bottom_right_x": 869.5341796875,
      "bottom_right_y": 434.4039306640625
    },
    {
      "cls": 0,
      "landing_status": -1,
      "top_left_x": 404.921875,
      "top_left_y": 184.27902221679688,
      "bottom_right_x": 624.54345703125,
      "bottom_right_y": 274.4736633300781
    },
    {
      "cls": 0,
      "landing_status": -1,
      "top_left_x": 467.1896667480469,
      "top_left_y": 619.99462890625,
      "bottom_right_x": 570.3046875,
      "bottom_right_y": 829.379638671875
    },
    {
      "cls": 0,
      "landing_status": -1,
      "top_left_x": 356.67657470703125,
      "top_left_y": 635.3740234375,
      "bottom_right_x": 457.00518798828125,
      "bottom_right_y": 853.735595703125
    },
    {
      "cls": 0,
      "landing_status": -1,
      "top_left_x": 955.2767333984375,
      "top_left_y": 198.859130859375,
      "bottom_right_x": 1154.0628662109375,
      "bottom_right_y": 288.629638671875
    },
    {
      "cls": 0,
      "landing_status": -1,
      "top_left_x": 244.97982788085938,
      "top_left_y": 618.404541015625,
      "bottom_right_x": 352.8858337402344,
      "bottom_right_y": 821.8673095703125
    },
    {
      "cls": 0,
      "landing_status": -1,
      "top_left_x": 582.379638671875,
      "top_left_y": 623.7021484375,
      "bottom_right_x": 680.3271484375,
      "bottom_right_y": 842.706787109375
    },
    {
      "cls": 0,
      "landing_status": -1,
      "top_left_x": 180.2181396484375,
      "top_left_y": 182.47824096679688,
      "bottom_right_x": 370.70513916015625,
      "bottom_right_y": 275.5564880371094
    },
    {
      "cls": 0,
      "landing_status": -1,
      "top_left_x": 819.4227905273438,
      "top_left_y": 626.614501953125,
      "bottom_right_x": 915.0062866210938,
      "bottom_right_y": 824.6025390625
    },
    {
      "cls": 0,
      "landing_status": -1,
      "top_left_x": 26.972396850585938,
      "top_left_y": 600.1402587890625,
      "bottom_right_x": 135.6925048828125,
      "bottom_right_y": 813.0872802734375
    },
    {
      "cls": 0,
      "landing_status": -1,
      "top_left_x": 1677.344970703125,
      "top_left_y": 242.56643676757812,
      "bottom_right_x": 1909.7958984375,
      "bottom_right_y": 341.2722473144531
    },
    {
      "cls": 0,
      "landing_status": -1,
      "top_left_x": 136.63143920898438,
      "top_left_y": 616.3013916015625,
      "bottom_right_x": 245.94790649414062,
      "bottom_right_y": 802.8804931640625
    },
    {
      "cls": 0,
      "landing_status": -1,
      "top_left_x": 708.6026611328125,
      "top_left_y": 628.6024169921875,
      "bottom_right_x": 802.8779296875,
      "bottom_right_y": 844.0408935546875
    },
    {
      "cls": 0,
      "landing_status": -1,
      "top_left_x": 934.121826171875,
      "top_left_y": 661.01708984375,
      "bottom_right_x": 1025.41845703125,
      "bottom_right_y": 875.2099609375
    },
    {
      "cls": 0,
      "landing_status": -1,
      "top_left_x": 1040.9189453125,
      "top_left_y": 654.1109619140625,
      "bottom_right_x": 1126.697265625,
      "bottom_right_y": 853.5748291015625
    }
  ],
  "detected_translations": [
    {
      "translation_x": 6.421427536010742,
      "translation_y": -76.08325958251953
    }
  ]
}