{
  "id": "frame_1853",
  "user": "NPC-A\u0130",
  "frame": "frame_1853",
  "detected_objects": [
    {
      "cls": 0.0,
      "top_left_x": 590.55078125,
      "top_left_y": 347.3657531738281,
      "bottom_right_x": 775.712890625,
      "bottom_right_y": 441.6669616699219
    },
    {
      "cls": 0.0,
      "top_left_x": 466.89056396484375,
      "top_left_y": 177.36947631835938,
      "bottom_right_x": 666.0131225585938,
      "bottom_right_y": 269.4248962402344
    },
    {
      "cls": 0.0,
      "top_left_x": 931.4937133789062,
      "top_left_y": 219.02491760253906,
      "bottom_right_x": 1148.4736328125,
      "bottom_right_y": 320.02685546875
    },
    {
      "cls": 0.0,
      "top_left_x": 1685.138916015625,
      "top_left_y": 907.587646484375,
      "bottom_right_x": 1790.197509765625,
      "bottom_right_y": 1079.112060546875
    },
    {
      "cls": 0.0,
      "top_left_x": 329.625244140625,
      "top_left_y": 605.7125244140625,
      "bottom_right_x": 433.6846923828125,
      "bottom_right_y": 804.543701171875
    },
    {
      "cls": 0.0,
      "top_left_x": 0.0,
      "top_left_y": 599.7459106445312,
      "bottom_right_x": 96.31861877441406,
      "bottom_right_y": 808.1654663085938
    },
    {
      "cls": 0.0,
      "top_left_x": 97.315673828125,
      "top_left_y": 602.2453002929688,
      "bottom_right_x": 208.42840576171875,
      "bottom_right_y": 818.7026977539062
    },
    {
      "cls": 0.0,
      "top_left_x": 222.64158630371094,
      "top_left_y": 606.7576904296875,
      "bottom_right_x": 315.96728515625,
      "bottom_right_y": 822.5386962890625
    },
    {
      "cls": 0.0,
      "top_left_x": 1170.13671875,
      "top_left_y": 223.16659545898438,
      "bottom_right_x": 1392.8525390625,
      "bottom_right_y": 324.3608093261719
    },
    {
      "cls": 0.0,
      "top_left_x": 0.0,
      "top_left_y": 164.75564575195312,
      "bottom_right_x": 141.90464782714844,
      "bottom_right_y": 254.25180053710938
    }
  ],
  "detected_translations": [
    {
      "translation_x": 17.47945365905762,
      "translation_y": -76.81112594604492
    }
  ]
}