{
  "id": "frame_1780",
  "user": "NPC-A\u0130",
  "frame": "frame_1780",
  "detected_objects": [
    {
      "cls": 0.0,
      "top_left_x": 251.9349365234375,
      "top_left_y": 380.2347412109375,
      "bottom_right_x": 438.52703857421875,
      "bottom_right_y": 477.26092529296875
    },
    {
      "cls": 0.0,
      "top_left_x": 1095.7342529296875,
      "top_left_y": 211.6764373779297,
      "bottom_right_x": 1185.1563720703125,
      "bottom_right_y": 429.32403564453125
    },
    {
      "cls": 0.0,
      "top_left_x": 963.1007080078125,
      "top_left_y": 761.2535400390625,
      "bottom_right_x": 1065.0020751953125,
      "bottom_right_y": 973.9849853515625
    },
    {
      "cls": 0.0,
      "top_left_x": 1575.13427734375,
      "top_left_y": 224.99249267578125,
      "bottom_right_x": 1690.33154296875,
      "bottom_right_y": 432.0477294921875
    },
    {
      "cls": 0.0,
      "top_left_x": 1462.1572265625,
      "top_left_y": 234.4945068359375,
      "bottom_right_x": 1556.24462890625,
      "bottom_right_y": 426.57391357421875
    },
    {
      "cls": 0.0,
      "top_left_x": 1331.324951171875,
      "top_left_y": 242.61463928222656,
      "bottom_right_x": 1430.707763671875,
      "bottom_right_y": 436.5225830078125
    },
    {
      "cls": 0.0,
      "top_left_x": 617.9674072265625,
      "top_left_y": 857.1876220703125,
      "bottom_right_x": 711.3634033203125,
      "bottom_right_y": 1070.7476806640625
    },
    {
      "cls": 0.0,
      "top_left_x": 1172.029296875,
      "top_left_y": 943.13720703125,
      "bottom_right_x": 1257.35009765625,
      "bottom_right_y": 1080.0
    },
    {
      "cls": 0.0,
      "top_left_x": 1695.219970703125,
      "top_left_y": 235.07901000976562,
      "bottom_right_x": 1795.788818359375,
      "bottom_right_y": 422.6926574707031
    },
    {
      "cls": 0.0,
      "top_left_x": 1396.59716796875,
      "top_left_y": 950.5418701171875,
      "bottom_right_x": 1487.1962890625,
      "bottom_right_y": 1079.131591796875
    },
    {
      "cls": 0.0,
      "top_left_x": 1225.438720703125,
      "top_left_y": 227.80517578125,
      "bottom_right_x": 1311.243408203125,
      "bottom_right_y": 420.30535888671875
    },
    {
      "cls": 0.0,
      "top_left_x": 1629.26904296875,
      "top_left_y": 930.81005859375,
      "bottom_right_x": 1741.3642578125,
      "bottom_right_y": 1079.73828125
    },
    {
      "cls": 0.0,
      "top_left_x": 1051.890869140625,
      "top_left_y": 910.0509033203125,
      "bottom_right_x": 1150.266845703125,
      "bottom_right_y": 1080.0
    },
    {
      "cls": 0.0,
      "top_left_x": 75.91934204101562,
      "top_left_y": 190.69024658203125,
      "bottom_right_x": 322.6799011230469,
      "bottom_right_y": 291.73419189453125
    },
    {
      "cls": 0.0,
      "top_left_x": 1758.00244140625,
      "top_left_y": 940.6517333984375,
      "bottom_right_x": 1872.422607421875,
      "bottom_right_y": 1079.5694580078125
    },
    {
      "cls": 0.0,
      "top_left_x": 0.0,
      "top_left_y": 197.2752685546875,
      "bottom_right_x": 91.96414184570312,
      "bottom_right_y": 287.18389892578125
    },
    {
      "cls": 1.0,
      "top_left_x": 1177.527099609375,
      "top_left_y": 120.04627990722656,
      "bottom_right_x": 1221.262939453125,
      "bottom_right_y": 158.05186462402344
    },
    {
      "cls": 0.0,
      "top_left_x": 1830.7791748046875,
      "top_left_y": 227.78256225585938,
      "bottom_right_x": 1920.0,
      "bottom_right_y": 426.9165954589844
    },
    {
      "cls": 1.0,
      "top_left_x": 1252.983642578125,
      "top_left_y": 60.11204528808594,
      "bottom_right_x": 1308.985595703125,
      "bottom_right_y": 91.51838684082031
    },
    {
      "cls": 0.0,
      "top_left_x": 1289.316650390625,
      "top_left_y": 940.521484375,
      "bottom_right_x": 1378.060302734375,
      "bottom_right_y": 1079.7620849609375
    }
  ],
  "detected_translations": [
    {
      "translation_x": 42.71045036315918,
      "translation_y": -77.53142318725585
    }
  ]
}