{
  "id": "frame_2585",
  "user": "NPC-A\u0130",
  "frame": "frame_2585",
  "detected_objects": [
    {
      "cls": 1.0,
      "top_left_x": 1694.4583740234375,
      "top_left_y": 659.3383178710938,
      "bottom_right_x": 1733.3397216796875,
      "bottom_right_y": 688.5623168945312
    },
    {
      "cls": 1.0,
      "top_left_x": 934.3853759765625,
      "top_left_y": 280.7154846191406,
      "bottom_right_x": 958.407958984375,
      "bottom_right_y": 304.7172546386719
    },
    {
      "cls": 1.0,
      "top_left_x": 889.91259765625,
      "top_left_y": 382.4974365234375,
      "bottom_right_x": 913.91015625,
      "bottom_right_y": 408.087890625
    },
    {
      "cls": 1.0,
      "top_left_x": 1357.17431640625,
      "top_left_y": 336.23828125,
      "bottom_right_x": 1389.44873046875,
      "bottom_right_y": 358.913330078125
    },
    {
      "cls": 1.0,
      "top_left_x": 776.2933349609375,
      "top_left_y": 471.2584533691406,
      "bottom_right_x": 808.6861572265625,
      "bottom_right_y": 488.3852233886719
    },
    {
      "cls": 1.0,
      "top_left_x": 841.1949462890625,
      "top_left_y": 569.096435546875,
      "bottom_right_x": 869.2393798828125,
      "bottom_right_y": 592.171142578125
    }
  ],
  "detected_translations": [
    {
      "translation_x": -69.36258430480957,
      "translation_y": -16.67941818237305
    }
  ]
}