{
  "id": "frame_1611",
  "user": "NPC-AI",
  "frame": "frame_1611",
  "detected_objects": [
    {
      "cls": 0,
      "landing_status": -1,
      "top_left_x": 304.59881591796875,
      "top_left_y": 505.0652770996094,
      "bottom_right_x": 396.79791259765625,
      "bottom_right_y": 687.3453369140625
    },
    {
      "cls": 0,
      "landing_status": -1,
      "top_left_x": 1723.303955078125,
      "top_left_y": 597.2669677734375,
      "bottom_right_x": 1837.23095703125,
      "bottom_right_y": 823.6822509765625
    },
    {
      "cls": 0,
      "landing_status": -1,
      "top_left_x": 547.8131103515625,
      "top_left_y": 512.3521728515625,
      "bottom_right_x": 637.889404296875,
      "bottom_right_y": 695.0709228515625
    },
    {
      "cls": 0,
      "landing_status": -1,
      "top_left_x": 424.1326904296875,
      "top_left_y": 514.0830078125,
      "bottom_right_x": 520.6998291015625,
      "bottom_right_y": 719.8282470703125
    },
    {
      "cls": 0,
      "landing_status": -1,
      "top_left_x": 36.69090270996094,
      "top_left_y": 748.9766235351562,
      "bottom_right_x": 218.57200622558594,
      "bottom_right_y": 832.5759887695312
    },
    {
      "cls": 0,
      "landing_status": -1,
      "top_left_x": 668.1795654296875,
      "top_left_y": 524.6767578125,
      "bottom_right_x": 753.5081787109375,
      "bottom_right_y": 704.8050537109375
    },
    {
      "cls": 0,
      "landing_status": -1,
      "top_left_x": 1437.052001953125,
      "top_left_y": 522.7670288085938,
      "bottom_right_x": 1534.537353515625,
      "bottom_right_y": 723.9642944335938
    },
    {
      "cls": 0,
      "landing_status": -1,
      "top_left_x": 69.92118835449219,
      "top_left_y": 499.2103271484375,
      "bottom_right_x": 174.79953002929688,
      "bottom_right_y": 692.240234375
    },
    {
      "cls": 0,
      "landing_status": -1,
      "top_left_x": 176.92425537109375,
      "top_left_y": 508.3193359375,
      "bottom_right_x": 270.22479248046875,
      "bottom_right_y": 682.6246337890625
    },
    {
      "cls": 0,
      "landing_status": -1,
      "top_left_x": 0.0,
      "top_left_y": 507.86474609375,
      "bottom_right_x": 58.81170654296875,
      "bottom_right_y": 687.65478515625
    },
    {
      "cls": 0,
      "landing_status": -1,
      "top_left_x": 76.70562744140625,
      "top_left_y": 1004.2173461914062,
      "bottom_right_x": 291.1874084472656,
      "bottom_right_y": 1079.71044921875
    },
    {
      "cls": 0,
      "landing_status": -1,
      "top_left_x": 1851.614501953125,
      "top_left_y": 997.9837646484375,
      "bottom_right_x": 1920.0,
      "bottom_right_y": 1079.3897705078125
    },
    {
      "cls": 0,
      "landing_status": -1,
      "top_left_x": 1859.817138671875,
      "top_left_y": 519.6708984375,
      "bottom_right_x": 1920.0,
      "bottom_right_y": 733.8780517578125
    },
    {
      "cls": 1,
      "landing_status": -1,
      "top_left_x": 1699.395751953125,
      "top_left_y": 386.4200439453125,
      "bottom_right_x": 1761.6474609375,
      "bottom_right_y": 416.08013916015625
    },
    {
      "cls": 0,
      "landing_status": -1,
      "top_left_x": 1728.496826171875,
      "top_left_y": 1002.6856079101562,
      "bottom_right_x": 1829.96875,
      "bottom_right_y": 1080.0
    },
    {
      "cls": 1,
      "landing_status": -1,
      "top_left_x": 1671.8232421875,
      "top_left_y": 465.93121337890625,
      "bottom_right_x": 1734.04736328125,
      "bottom_right_y": 494.1793212890625
    },
    {
      "cls": 1,
      "landing_status": -1,
      "top_left_x": 1676.2811279296875,
      "top_left_y": 437.558837890625,
      "bottom_right_x": 1726.6937255859375,
      "bottom_right_y": 462.6871337890625
    },
    {
      "cls": 1,
      "landing_status": -1,
      "top_left_x": 504.1159973144531,
      "top_left_y": 377.62567138671875,
      "bottom_right_x": 558.503662109375,
      "bottom_right_y": 408.27777099609375
    },
    {
      "cls": 1,
      "landing_status": -1,
      "top_left_x": 0.0,
      "top_left_y": 431.92645263671875,
      "bottom_right_x": 62.68347930908203,
      "bottom_right_y": 460.763427734375
    },
    {
      "cls": 1,
      "landing_status": -1,
      "top_left_x": 0.19068527221679688,
      "top_left_y": 405.639892578125,
      "bottom_right_x": 48.715450286865234,
      "bottom_right_y": 432.7548828125
    },
    {
      "cls": 1,
      "landing_status": -1,
      "top_left_x": 824.1460571289062,
      "top_left_y": 642.20166015625,
      "bottom_right_x": 851.2728881835938,
      "bottom_right_y": 679.600830078125
    },
    {
      "cls": 1,
      "landing_status": -1,
      "top_left_x": 855.221923828125,
      "top_left_y": 664.8489990234375,
      "bottom_right_x": 883.1187744140625,
      "bottom_right_y": 696.363525390625
    },
    {
      "cls": 1,
      "landing_status": -1,
      "top_left_x": 947.329833984375,
      "top_left_y": 369.1044006347656,
      "bottom_right_x": 975.7884521484375,
      "bottom_right_y": 391.4575500488281
    }
  ],
  "detected_translations": [
    {
      "translation_x": 77.9949504852295,
      "translation_y": -71.62245635986328
    }
  ]
}