{
  "id": "frame_1069",
  "user": "NPC-A\u0130",
  "frame": "frame_1069",
  "detected_objects": [
    {
      "cls": 0.0,
      "top_left_x": 1342.067138671875,
      "top_left_y": 313.5411071777344,
      "bottom_right_x": 1570.165283203125,
      "bottom_right_y": 419.3236389160156
    },
    {
      "cls": 0.0,
      "top_left_x": 358.32025146484375,
      "top_left_y": 683.3760986328125,
      "bottom_right_x": 466.54150390625,
      "bottom_right_y": 918.0931396484375
    },
    {
      "cls": 1.0,
      "top_left_x": 1066.921875,
      "top_left_y": 687.8057861328125,
      "bottom_right_x": 1106.567626953125,
      "bottom_right_y": 722.7421875
    },
    {
      "cls": 1.0,
      "top_left_x": 1008.171142578125,
      "top_left_y": 179.0645751953125,
      "bottom_right_x": 1038.666015625,
      "bottom_right_y": 214.89797973632812
    },
    {
      "cls": 1.0,
      "top_left_x": 1605.40966796875,
      "top_left_y": 692.2530517578125,
      "bottom_right_x": 1670.9912109375,
      "bottom_right_y": 736.3153076171875
    },
    {
      "cls": 1.0,
      "top_left_x": 1632.84716796875,
      "top_left_y": 692.8914184570312,
      "bottom_right_x": 1670.986572265625,
      "bottom_right_y": 736.9135131835938
    }
  ],
  "detected_translations": [
    {
      "translation_x": 80.93531875610351,
      "translation_y": 114.21939239501953
    }
  ]
}