{
  "id": "frame_1906",
  "user": "NPC-A\u0130",
  "frame": "frame_1906",
  "detected_objects": [
    {
      "cls": 0.0,
      "top_left_x": 182.3934326171875,
      "top_left_y": 624.3544311523438,
      "bottom_right_x": 290.6410827636719,
      "bottom_right_y": 836.3203735351562
    },
    {
      "cls": 0.0,
      "top_left_x": 1587.0667724609375,
      "top_left_y": 263.0816650390625,
      "bottom_right_x": 1832.0648193359375,
      "bottom_right_y": 364.0384521484375
    },
    {
      "cls": 0.0,
      "top_left_x": 652.10205078125,
      "top_left_y": 355.3289794921875,
      "bottom_right_x": 834.572265625,
      "bottom_right_y": 448.60699462890625
    },
    {
      "cls": 0.0,
      "top_left_x": 1115.013427734375,
      "top_left_y": 223.7994842529297,
      "bottom_right_x": 1316.448974609375,
      "bottom_right_y": 312.98101806640625
    },
    {
      "cls": 0.0,
      "top_left_x": 403.6173400878906,
      "top_left_y": 640.9920654296875,
      "bottom_right_x": 503.9812927246094,
      "bottom_right_y": 843.8345947265625
    },
    {
      "cls": 0.0,
      "top_left_x": 978.253173828125,
      "top_left_y": 650.9242553710938,
      "bottom_right_x": 1073.505615234375,
      "bottom_right_y": 847.9902954101562
    },
    {
      "cls": 0.0,
      "top_left_x": 626.1033325195312,
      "top_left_y": 645.0316162109375,
      "bottom_right_x": 723.3255004882812,
      "bottom_right_y": 853.9371337890625
    },
    {
      "cls": 0.0,
      "top_left_x": 297.5960693359375,
      "top_left_y": 639.7378540039062,
      "bottom_right_x": 399.568603515625,
      "bottom_right_y": 824.5278930664062
    },
    {
      "cls": 0.0,
      "top_left_x": 68.57986450195312,
      "top_left_y": 644.271240234375,
      "bottom_right_x": 176.82574462890625,
      "bottom_right_y": 833.00537109375
    },
    {
      "cls": 0.0,
      "top_left_x": 739.3342895507812,
      "top_left_y": 647.9343872070312,
      "bottom_right_x": 835.4093627929688,
      "bottom_right_y": 865.8256225585938
    },
    {
      "cls": 0.0,
      "top_left_x": 514.7783203125,
      "top_left_y": 659.9779052734375,
      "bottom_right_x": 611.52197265625,
      "bottom_right_y": 877.1778564453125
    },
    {
      "cls": 0.0,
      "top_left_x": 561.3162841796875,
      "top_left_y": 207.6716766357422,
      "bottom_right_x": 782.6658935546875,
      "bottom_right_y": 299.31597900390625
    },
    {
      "cls": 0.0,
      "top_left_x": 1091.092041015625,
      "top_left_y": 685.01025390625,
      "bottom_right_x": 1182.804443359375,
      "bottom_right_y": 902.05712890625
    },
    {
      "cls": 0.0,
      "top_left_x": 0.0,
      "top_left_y": 614.0095825195312,
      "bottom_right_x": 72.28453063964844,
      "bottom_right_y": 802.4126586914062
    },
    {
      "cls": 0.0,
      "top_left_x": 868.639404296875,
      "top_left_y": 651.7984619140625,
      "bottom_right_x": 957.04443359375,
      "bottom_right_y": 869.6448974609375
    },
    {
      "cls": 0.0,
      "top_left_x": 1197.79541015625,
      "top_left_y": 678.5015258789062,
      "bottom_right_x": 1291.7041015625,
      "bottom_right_y": 899.0414428710938
    },
    {
      "cls": 0.0,
      "top_left_x": 1844.1961669921875,
      "top_left_y": 273.7125244140625,
      "bottom_right_x": 1920.0,
      "bottom_right_y": 367.998291015625
    },
    {
      "cls": 0.0,
      "top_left_x": 335.33807373046875,
      "top_left_y": 201.29580688476562,
      "bottom_right_x": 528.4678955078125,
      "bottom_right_y": 301.8821105957031
    }
  ],
  "detected_translations": [
    {
      "translation_x": 2.9130855560302735,
      "translation_y": -75.55611267089844
    }
  ]
}