{
  "id": "frame_1905",
  "user": "NPC-AI",
  "frame": "frame_1905",
  "detected_objects": [
    {
      "cls": 0,
      "landing_status": -1,
      "top_left_x": 1578.433349609375,
      "top_left_y": 262.3253173828125,
      "bottom_right_x": 1823.163818359375,
      "bottom_right_y": 360.7117919921875
    },
    {
      "cls": 0,
      "landing_status": -1,
      "top_left_x": 969.751708984375,
      "top_left_y": 647.9578857421875,
      "bottom_right_x": 1065.947998046875,
      "bottom_right_y": 846.85986328125
    },
    {
      "cls": 0,
      "landing_status": -1,
      "top_left_x": 617.5122680664062,
      "top_left_y": 641.107177734375,
      "bottom_right_x": 717.1998901367188,
      "bottom_right_y": 851.76611328125
    },
    {
      "cls": 0,
      "landing_status": -1,
      "top_left_x": 1106.28662109375,
      "top_left_y": 220.12440490722656,
      "bottom_right_x": 1307.99951171875,
      "bottom_right_y": 310.4755859375
    },
    {
      "cls": 0,
      "landing_status": -1,
      "top_left_x": 61.3739013671875,
      "top_left_y": 640.623291015625,
      "bottom_right_x": 167.50485229492188,
      "bottom_right_y": 829.7705078125
    },
    {
      "cls": 0,
      "landing_status": -1,
      "top_left_x": 505.9024658203125,
      "top_left_y": 657.2772216796875,
      "bottom_right_x": 605.95947265625,
      "bottom_right_y": 876.2196044921875
    },
    {
      "cls": 0,
      "landing_status": -1,
      "top_left_x": 732.4430541992188,
      "top_left_y": 646.276611328125,
      "bottom_right_x": 828.4683227539062,
      "bottom_right_y": 865.1375732421875
    },
    {
      "cls": 0,
      "landing_status": -1,
      "top_left_x": 394.634765625,
      "top_left_y": 639.1544799804688,
      "bottom_right_x": 499.435302734375,
      "bottom_right_y": 843.2870483398438
    },
    {
      "cls": 0,
      "landing_status": -1,
      "top_left_x": 859.824462890625,
      "top_left_y": 649.6131591796875,
      "bottom_right_x": 952.4075927734375,
      "bottom_right_y": 865.4434814453125
    },
    {
      "cls": 0,
      "landing_status": -1,
      "top_left_x": 175.94366455078125,
      "top_left_y": 621.2159423828125,
      "bottom_right_x": 281.84014892578125,
      "bottom_right_y": 833.5338134765625
    },
    {
      "cls": 0,
      "landing_status": -1,
      "top_left_x": 288.5638732910156,
      "top_left_y": 636.77880859375,
      "bottom_right_x": 392.9449768066406,
      "bottom_right_y": 823.3349609375
    },
    {
      "cls": 0,
      "landing_status": -1,
      "top_left_x": 655.419921875,
      "top_left_y": 353.81964111328125,
      "bottom_right_x": 838.674560546875,
      "bottom_right_y": 445.2816162109375
    },
    {
      "cls": 0,
      "landing_status": -1,
      "top_left_x": 1083.40087890625,
      "top_left_y": 681.8226318359375,
      "bottom_right_x": 1176.65185546875,
      "bottom_right_y": 900.295654296875
    },
    {
      "cls": 0,
      "landing_status": -1,
      "top_left_x": 1190.41064453125,
      "top_left_y": 674.8714599609375,
      "bottom_right_x": 1279.66259765625,
      "bottom_right_y": 877.52197265625
    },
    {
      "cls": 0,
      "landing_status": -1,
      "top_left_x": 1837.88232421875,
      "top_left_y": 263.162109375,
      "bottom_right_x": 1920.0,
      "bottom_right_y": 363.5220947265625
    },
    {
      "cls": 0,
      "landing_status": -1,
      "top_left_x": 554.15185546875,
      "top_left_y": 202.89825439453125,
      "bottom_right_x": 774.291748046875,
      "bottom_right_y": 295.4149169921875
    },
    {
      "cls": 0,
      "landing_status": -1,
      "top_left_x": 330.2735595703125,
      "top_left_y": 203.68386840820312,
      "bottom_right_x": 519.76708984375,
      "bottom_right_y": 293.2216491699219
    },
    {
      "cls": 0,
      "landing_status": -1,
      "top_left_x": 0.0,
      "top_left_y": 610.7085571289062,
      "bottom_right_x": 61.4078254699707,
      "bottom_right_y": 798.1528930664062
    },
    {
      "cls": 1,
      "landing_status": -1,
      "top_left_x": 1858.791015625,
      "top_left_y": 57.95552444458008,
      "bottom_right_x": 1912.3544921875,
      "bottom_right_y": 102.60380554199219
    },
    {
      "cls": 1,
      "landing_status": -1,
      "top_left_x": 459.0404052734375,
      "top_left_y": 577.8483276367188,
      "bottom_right_x": 510.4366455078125,
      "bottom_right_y": 614.3662719726562
    }
  ],
  "detected_translations": [
    {
      "translation_x": 3.0988109588623045,
      "translation_y": -75.61479415893555
    }
  ]
}