{
  "id": "frame_1814",
  "user": "NPC-AI",
  "frame": "frame_1814",
  "detected_objects": [
    {
      "cls": 0,
      "landing_status": -1,
      "top_left_x": 423.59820556640625,
      "top_left_y": 365.5763244628906,
      "bottom_right_x": 608.3567504882812,
      "bottom_right_y": 458.3426818847656
    },
    {
      "cls": 0,
      "landing_status": -1,
      "top_left_x": 364.05517578125,
      "top_left_y": 200.98922729492188,
      "bottom_right_x": 575.3316650390625,
      "bottom_right_y": 298.3490905761719
    },
    {
      "cls": 0,
      "landing_status": -1,
      "top_left_x": 1457.790771484375,
      "top_left_y": 780.1776123046875,
      "bottom_right_x": 1574.18701171875,
      "bottom_right_y": 999.463623046875
    },
    {
      "cls": 0,
      "landing_status": -1,
      "top_left_x": 1599.138916015625,
      "top_left_y": 220.13272094726562,
      "bottom_right_x": 1705.806884765625,
      "bottom_right_y": 445.6619567871094
    },
    {
      "cls": 0,
      "landing_status": -1,
      "top_left_x": 584.0885620117188,
      "top_left_y": 201.10708618164062,
      "bottom_right_x": 810.0827026367188,
      "bottom_right_y": 298.85723876953125
    },
    {
      "cls": 0,
      "landing_status": -1,
      "top_left_x": 1107.29296875,
      "top_left_y": 877.623046875,
      "bottom_right_x": 1198.04638671875,
      "bottom_right_y": 1077.6962890625
    },
    {
      "cls": 0,
      "landing_status": -1,
      "top_left_x": 1735.77880859375,
      "top_left_y": 238.10235595703125,
      "bottom_right_x": 1844.439453125,
      "bottom_right_y": 434.22283935546875
    },
    {
      "cls": 0,
      "landing_status": -1,
      "top_left_x": 1674.2774658203125,
      "top_left_y": 967.430908203125,
      "bottom_right_x": 1776.8126220703125,
      "bottom_right_y": 1078.293212890625
    },
    {
      "cls": 0,
      "landing_status": -1,
      "top_left_x": 0.0,
      "top_left_y": 160.53945922851562,
      "bottom_right_x": 106.34964752197266,
      "bottom_right_y": 251.07989501953125
    },
    {
      "cls": 0,
      "landing_status": -1,
      "top_left_x": 1844.6478271484375,
      "top_left_y": 252.34356689453125,
      "bottom_right_x": 1920.0,
      "bottom_right_y": 451.41070556640625
    },
    {
      "cls": 0,
      "landing_status": -1,
      "top_left_x": 1559.912353515625,
      "top_left_y": 933.9580078125,
      "bottom_right_x": 1663.350341796875,
      "bottom_right_y": 1078.915771484375
    },
    {
      "cls": 0,
      "landing_status": -1,
      "top_left_x": 1790.411865234375,
      "top_left_y": 965.5150146484375,
      "bottom_right_x": 1910.121826171875,
      "bottom_right_y": 1080.0
    },
    {
      "cls": 1,
      "landing_status": -1,
      "top_left_x": 1618.3099365234375,
      "top_left_y": 131.73175048828125,
      "bottom_right_x": 1678.7156982421875,
      "bottom_right_y": 175.74322509765625
    },
    {
      "cls": 1,
      "landing_status": -1,
      "top_left_x": 1632.068603515625,
      "top_left_y": 157.99610900878906,
      "bottom_right_x": 1693.571533203125,
      "bottom_right_y": 194.5311737060547
    },
    {
      "cls": 1,
      "landing_status": -1,
      "top_left_x": 1589.310546875,
      "top_left_y": 696.9910888671875,
      "bottom_right_x": 1650.3896484375,
      "bottom_right_y": 739.7860107421875
    }
  ],
  "detected_translations": [
    {
      "translation_x": 30.29242057800293,
      "translation_y": -77.02051620483398
    }
  ]
}