{
  "id": "frame_2517",
  "user": "NPC-A\u0130",
  "frame": "frame_2517",
  "detected_objects": [
    {
      "cls": 1.0,
      "top_left_x": 526.2694091796875,
      "top_left_y": 533.520263671875,
      "bottom_right_x": 552.3067626953125,
      "bottom_right_y": 553.594482421875
    },
    {
      "cls": 1.0,
      "top_left_x": 735.9559936523438,
      "top_left_y": 812.7933959960938,
      "bottom_right_x": 763.7266235351562,
      "bottom_right_y": 838.2525024414062
    },
    {
      "cls": 1.0,
      "top_left_x": 1453.488037109375,
      "top_left_y": 801.3472900390625,
      "bottom_right_x": 1479.969482421875,
      "bottom_right_y": 835.007080078125
    },
    {
      "cls": 1.0,
      "top_left_x": 857.5330810546875,
      "top_left_y": 751.0530395507812,
      "bottom_right_x": 881.9578857421875,
      "bottom_right_y": 772.1609497070312
    },
    {
      "cls": 1.0,
      "top_left_x": 1014.11572265625,
      "top_left_y": 184.4107666015625,
      "bottom_right_x": 1030.42724609375,
      "bottom_right_y": 210.490966796875
    },
    {
      "cls": 1.0,
      "top_left_x": 1245.2247314453125,
      "top_left_y": 192.6579132080078,
      "bottom_right_x": 1269.2508544921875,
      "bottom_right_y": 214.93223571777344
    }
  ],
  "detected_translations": [
    {
      "translation_x": -62.6048999786377,
      "translation_y": -12.319481658935548
    }
  ]
}